{
	"画像": "https://img.game8.jp/4637890/929fee00f24797a03ee7f0cb0dcdd4cc.png/show",
	"共通": {
		"名前": "キキラトV.2",
		"レアリティ": "星3",
		"属性": "光",
		"職業": "ナイト"
	},
	"ステータス": {
		"攻撃力": {
			"初期値": "235",
			"最大値": "667"
		},
		"生命力": {
			"初期値": "2314",
			"最大値": "5704"
		},
		"スピード": {
			"初期値": "90",
			"最大値": "90"
		},
		"防御力": {
			"初期値": "304",
			"最大値": "749"
		},
		"クリティカル発生率": {
			"初期値": "15.0%",
			"最大値": "15.0%"
		},
		"クリティカルダメージ": {
			"初期値": "150.0%",
			"最大値": "150.0%"
		},
		"連続攻撃発生率": {
			"初期値": "5.0%",
			"最大値": "5.0%"
		},
		"効果命中率": {
			"初期値": "0.0%",
			"最大値": "0.0%"
		},
		"効果命中率DOWN": {
			"初期値": "0.0%",
			"最大値": "18.0%"
		}
	},
	"陣形効果": {
		"刻印展開": [
			{
				"生命力": "120"
			},
			{
				"生命力": "180"
			},
			{
				"生命力": "240"
			},
			{
				"生命力": "300"
			},
			{
				"生命力": "360"
			},
			{
				"生命力": "420"
			},
			{
				"生命力": "480"
			}
		],
		"刻印集中": [
			{
				"防御力": "18"
			},
			{
				"防御力": "27"
			},
			{
				"防御力": "36"
			},
			{
				"防御力": "45"
			},
			{
				"防御力": "54"
			},
			{
				"防御力": "63"
			},
			{
				"防御力": "72"
			}
		]
	},
	"スキル": [
		{
			"スキル名": "連射",
			"説明": [
				"敵単体に攻撃し、65%の確率で強化効果を1つ解除する。自身の防御力が高いほどダメージがUPする。",
				"(魂力1獲得)"
			],
			"強化効果": [
				"ダメージ5%UP",
				"効果発生率10％UP",
				"ダメージ10%UP",
				"効果発生率15％UP",
				"ダメージ15%UP"
			],
			"強化素材": [
				{
					"聖痕の葉": "120"
				},
				{
					"聖痕の葉": "270"
				},
				{
					"聖痕の葉": "470",
					"スライムゼリー": "3"
				},
				{
					"聖痕の葉": "740",
					"スライムゼリー": "4"
				},
				{
					"聖痕の葉": "1100",
					"スライムゼリー": "5"
				}
			]
		},
		{
			"スキル名": "防御システム構築",
			"説明": [
				"攻撃後、自身の防御力が7.0%UPする。最大5回まで累積する。"
			],
			"強化効果": [
				"防御力0.5%UP",
				"防御力0.5%UP",
				"防御力0.5%UP",
				"防御力0.5%UP",
				"防御力1%UP"
			],
			"強化素材": [
				{
					"聖痕の葉": "120"
				},
				{
					"聖痕の葉": "270"
				},
				{
					"聖痕の葉": "470",
					"スライムゼリー": "3"
				},
				{
					"聖痕の葉": "740",
					"スライムゼリー": "4"
				},
				{
					"聖痕の葉": "1100",
					"スライムゼリー": "5"
				}
			]
		},
		{
			"スキル名": "掃除モード起動\n(スキルターン:3)",
			"説明": [
				"敵全体に攻撃し、60%の確率で命中率DOWNを1ターンの間付与した後、自身に反撃を2ターンの間付与する。自身の防御力が高いほどダメージがUPする。",
				"(魂力2獲得)"
			],
			"強化効果": [
				"ダメージ5%UP",
				"効果発生率5%UP",
				"ダメージ10%UP",
				"効果発生率10%UP",
				"ダメージ15%UP"
			],
			"強化素材": [
				{
					"聖痕の葉": "120"
				},
				{
					"聖痕の葉": "270"
				},
				{
					"聖痕の葉": "470",
					"スライムゼリー": "3"
				},
				{
					"聖痕の葉": "740",
					"スライムゼリー": "4"
				},
				{
					"聖痕の葉": "1100",
					"スライムゼリー": "5"
				}
			]
		}
	]
}