{
	"画像": "https://img.game8.jp/3771176/6434b991e3bd438ebb179352cd126360.png/show",
	"共通": {
		"名前": "求道者アイテール",
		"レアリティ": "星4",
		"属性": "光",
		"職業": "メイジ"
	},
	"ステータス": {
		"攻撃力": {
			"初期値": "580",
			"最大値": "1252"
		},
		"生命力": {
			"初期値": "2549",
			"最大値": "4612"
		},
		"スピード": {
			"初期値": "107",
			"最大値": "107"
		},
		"防御力": {
			"初期値": "394",
			"最大値": "627"
		},
		"クリティカル発生率": {
			"初期値": "15.0%",
			"最大値": "23.0%"
		},
		"クリティカルダメージ": {
			"初期値": "150.0%",
			"最大値": "150.0%"
		},
		"連続攻撃発生率": {
			"初期値": "5.0%",
			"最大値": "5.0%"
		},
		"効果命中率": {
			"初期値": "0.0%",
			"最大値": "0.0%"
		},
		"効果命中率DOWN": {
			"初期値": "0.0%",
			"最大値": "0.0%"
		}
	},
	"陣形効果": {
		"刻印展開": [
			{
				"生命力": "2.4%"
			},
			{
				"生命力": "3.6%"
			},
			{
				"生命力": "4.8%"
			},
			{
				"生命力": "6%"
			},
			{
				"生命力": "7.2%"
			},
			{
				"生命力": "8.4%"
			}
		],
		"刻印集中": [
			{
				"攻撃力": "4%"
			},
			{
				"攻撃力": "6%"
			},
			{
				"攻撃力": "8%"
			},
			{
				"攻撃力": "10%"
			},
			{
				"攻撃力": "12%"
			},
			{
				"攻撃力": "14%"
			}
		]
	},
	"スキル": [
		{
			"スキル名": "精霊の囁き",
			"説明": [
				"敵単体に攻撃し、25%の確率でスピードDOWNを2ターンの間付与する。",
				"(魂力1獲得)"
			],
			"強化効果": [
				"ダメージ5%UP",
				"ダメージ10%UP",
				"効果発生率10%UP",
				"効果発生率15%UP",
				"ダメージ15%UP"
			],
			"強化素材": [
				{
					"モラゴラ": "1"
				},
				{
					"モラゴラ": "1"
				},
				{
					"モラゴラ": "1",
					"ベルマウスの徽章": "1"
				},
				{
					"モラゴラ": "2",
					"ベルマウスの徽章": "3"
				},
				{
					"モラゴラゴ": "1",
					"偽善の心臓": "2"
				}
			]
		},
		{
			"スキル名": "精霊の加護\n\n(スキルターン:3)",
			"説明": [
				"敵単体に攻撃し、味方全体の生命力を回復し、シールドを2ターンの間付与する。自身の攻撃力が高いほど回復量とシールド効果がUPする。",
				"(魂力2獲得)"
			],
			"強化効果": [
				"ダメージ5%UP",
				"ダメージ5%UP",
				"ダメージ10%UP",
				"ダメージ10%UP",
				"ダメージ10%UP"
			],
			"強化素材": [
				{
					"モラゴラ": "1"
				},
				{
					"モラゴラ": "1"
				},
				{
					"モラゴラ": "1",
					"ベルマウスの徽章": "1"
				},
				{
					"モラゴラ": "2",
					"ベルマウスの徽章": "3"
				},
				{
					"モラゴラゴ": "1",
					"偽善の心臓": "2"
				}
			]
		},
		{
			"スキル名": "力の波動\n\n(スキルターン:5)",
			"説明": [
				"敵単体に攻撃し、強化効果をすべて解除する。攻撃力が最も高い味方単体に攻撃力UPを2ターンの間付与し、アクションゲージを50%UPさせる。",
				"(魂力2獲得)"
			],
			"強化効果": [
				"ダメージ5%UP",
				"ダメージ5%UP",
				"スキルターン1減少",
				"ダメージ10%UP",
				"ダメージ10%UP"
			],
			"強化素材": [
				{
					"モラゴラ": "1"
				},
				{
					"モラゴラ": "1"
				},
				{
					"モラゴラ": "1",
					"ベルマウスの徽章": "1"
				},
				{
					"モラゴラ": "2",
					"ベルマウスの徽章": "3"
				},
				{
					"モラゴラゴ": "1",
					"偽善の心臓": "2"
				}
			]
		}
	]
}